chitanda/__init__.py
chitanda/__main__.py
chitanda/bot.py
chitanda/commands.py
chitanda/config.py
chitanda/database.py
chitanda/decorators.py
chitanda/errors.py
chitanda/listeners/__init__.py
chitanda/listeners/discord.py
chitanda/listeners/irc.py
chitanda/loader.py
chitanda/modules/__init__.py
chitanda/modules/aliases.py
chitanda/modules/choose.py
chitanda/modules/github_relay.py
chitanda/modules/help.py
chitanda/modules/irc_channels/__init__.py
chitanda/modules/irc_channels/join.py
chitanda/modules/irc_channels/migrations/0001.sql
chitanda/modules/irc_channels/part.py
chitanda/modules/lastfm/__init__.py
chitanda/modules/lastfm/lastfm.py
chitanda/modules/lastfm/migrations/0001.sql
chitanda/modules/lastfm/set.py
chitanda/modules/lastfm/unset.py
chitanda/modules/quotes/__init__.py
chitanda/modules/quotes/add.py
chitanda/modules/quotes/delete.py
chitanda/modules/quotes/fetch.py
chitanda/modules/quotes/find.py
chitanda/modules/quotes/migrations/0001.sql
chitanda/modules/reload.py
chitanda/modules/say.py
chitanda/modules/sed.py
chitanda/modules/tell/__init__.py
chitanda/modules/tell/migrations/0001.sql
chitanda/modules/titles.py
chitanda/modules/urbandictionary.py
chitanda/modules/wolframalpha.py
chitanda/util.py
chitanda-0.0.4.dist-info/entry_points.txt
chitanda-0.0.4.dist-info/WHEEL
chitanda-0.0.4.dist-info/METADATA
chitanda-0.0.4.dist-info/RECORD
