Metadata-Version: 2.1
Name: chitanda
Version: 0.0.4
Summary: An extensible Discord & IRC bot.
Home-page: https://github.com/dazuling/chitanda
License: GPL-3.0
Author: dazuling
Author-email: azuline@riseup.net
Requires-Python: >=3.7,<4.0
Classifier: License :: OSI Approved :: GNU General Public License v3 (GPLv3)
Classifier: Programming Language :: Python :: 3
Classifier: Programming Language :: Python :: 3.7
Requires-Dist: aiohttp (>=3.5,<4.0)
Requires-Dist: appdirs (>=1.4,<2.0)
Requires-Dist: click (>=7.0,<8.0)
Requires-Dist: discord.py (>=1.2,<2.0)
Requires-Dist: gevent (>=1.4,<2.0)
Requires-Dist: huey (>=1.10,<2.0)
Requires-Dist: pydle (>=0.9.1,<0.10.0)
Requires-Dist: requests (>=2.22,<3.0)
Project-URL: Repository, https://github.com/dazuling/chitanda
